tag_mne/__init__.py
tag_mne/main.py
tag_mne/mne_utils.py
tag_mne/utils.py
tag_mne-0.0.8.dist-info/licenses/LICENSE
tag_mne-0.0.8.dist-info/METADATA
tag_mne-0.0.8.dist-info/WHEEL
tag_mne-0.0.8.dist-info/top_level.txt
tag_mne-0.0.8.dist-info/RECORD
