Metadata-Version: 2.4
Name: tag-mne
Version: 0.0.8
Summary: python library for working on mne tag
Home-page: https://github.com/simonkojima/tag-mne
Author: Simon Kojima
License: MIT
License-File: LICENSE
Requires-Dist: numpy
Requires-Dist: mne>=1.8
Dynamic: author
Dynamic: description
Dynamic: description-content-type
Dynamic: home-page
Dynamic: license
Dynamic: license-file
Dynamic: requires-dist
Dynamic: summary
